<document xml:lang="sme" id="no_id"><header><title/><genre code="Len"/><author><unknown/></author><wordcount>272</wordcount><conversion_status type="correct"/><availability><free/></availability><multilingual/><metadata><uncomplete/></metadata><version>XSLtemplate $Revision: 64438 $; file-specific xsl  Revision; common.xsl  $Revision$; </version></header><body>
<p xml:lang="mrj">#8.12.12</p>
<p>Sámi Siida čielggada sámegielat skuvllaid ja beaiveruovttuid ásaheami</p>
<p>Ođđasat jahkečoahkkimis</p>
<p>Sámi Siidda jahkečoahkkin ii leat duđavaš dálá <errormorphsyn>dilis<correct errorinfo="noun,advl,comsg,logsg,case">diliin</correct></errormorphsyn> sámegielat oahpahusas ja beaiveruovttuin. Danne mearridii čielgadišgoahtit sámegielat skuvllaid ja beaiveruovttuid ásaheami. Ođđa jođiheaddji Torkel Rasmussen lohká dákkár ásahemiid leat sihke vejolažžan ja ruđalaččat gánnehahttin.</p>
<p>Ohcejoga gielddaráđđehus lea sihkastan eret guokte oahpaheaddjiidvirggi ja doaimmaha sámegielat beaiveruovttuid <errormorphsyn>dohkkemeahttumis<correct errorinfo="adj,attr,attr,locsg,infl">dohkkemeahttun</correct></errormorphsyn> gáržžes latnjadilis.</p>
<p>Sámi Siida oaidná nu buriid ruhtadanvejolašvuođaid sámegielat skuvllain ja beaiveruovttuin ahte jáhkká iežas nákcet sihke ásahit ja doaimmahit skuvllaid ja beaiveruovttuid.</p>
<p>- Suoma stáhta doarju priváhta skuvllaid ja beaiveruovttuid ja gokčá sámegielat oahpahusa <errorort>oahpaheaddjigoluid<correct errorinfo="noun,cmp,svow">oahpaheaddjegoluid</correct></errorort>. Dasa lassin juolluda Sámediggi doarjaga sámegielat beaiveruovttuide ja giellabesiide. Lea maid vejolaš vuovdit buori hattis beaiveruovttu sajiid <errorort>gránnjágielddaide<correct errorinfo="noun,init">kránnjágielddaide</correct></errorort>. Dan dahká Ohcejoga gielda dál ja dine bures das, čilge Sámi Siidda jođiheaddji Torkel Rasmussen</p>
<p>Sámi Siidda jahkečoahkkin mearridii muđui joatkit dálá doaimmaiguin dego mannan jagi, <errorort>omd<correct errorinfo="abbr,punct">omd.</correct></errorort> <errorsyn>mánáid ja <errorort>nuoraiddoaimmaguin<correct errorinfo="noun,typo">nuoraiddoaimmaiguin</correct></errorort><correct errorinfo="noun,hyph">mánáid- ja nuoraiddoaimmaiguin</correct></errorsyn>. Čoahkkima beavdegirji ja doaibmaplána biddjojuvvo <errorort>lohkanláhkai<correct errorinfo="adv,notcmp">lohkan láhkai</correct></errorort> go lea dárkkistuvvon.</p>
<p>Das namahuvvo dušše ahte njuolggadusaide leat boahtán <errormorphsyn><errormorphsyn>guokte nuppástusa mii<correct errorinfo="rel,subj,nompl,nomsg,kongr">guokte nuppástusa mat</correct></errormorphsyn> nanne<correct errorinfo="verb,fin,pl3prs,sg3prs,kongr">guokte nuppástusa mat nannejit</correct></errormorphsyn> sámegiela sajádaga searvvi doaimmain ja deattuhit searvvi doaimma davvisámegielat searvin mii doarju, nanne ja ealáskahttá sámegiela.</p>
<p>Ođđa 2 § <errorsyn>Searvvi čoahkkin ja beavdegirjegiella lea sámegiella<correct errorinfo="noun,hyph">Searvvi čoahkkin- ja beavdegirjegiella lea sámegiella</correct></errorsyn></p>
<p>Ođđa 3 § Searvvi ulbmilin lea doarjut, nannet ja ealáskahttit davvisámegiela. Dan lassin ulbmilin lea dorvvastit sámiid vuoigatvuođaid doalahit, ollašuhttit ja ovddidit iežas kultuvrra sihke doarjut ja ovddidit sámi kultuvrralaš, sosiálalaš, vuoigatvuođalaš ja almmolaš ekonomalaš <errorort>vikkamušaid<correct errorinfo="noun,conc">viggamušaid</correct></errorort> ja maiddái bargat ovttas riikka rájáid badjel.</p>
<p>Ságajođiheaddji Torkel Rasmussen lassin válljejuvvui <errorortreal>várraságajođiheaddjin<correct errorinfo="noun,svow">várreságajođiheaddjin</correct></errorortreal> Karen Kitti, <errorort>stivralahttun<correct errorinfo="noun,cmp,nomsg,gensg">stivrralahttun</correct></errorort> Heidi Kitti, Niilo Kalevi Länsman ja Siskko Länsman Várrelahttun: Erika Sarivaara, Maarit K. Peski, Jouni Esa <errorort>Nuosuniemi<correct errorinfo="prop,meta">Nousuniemi</correct></errorort>, Juha Pohjanraito ja Heidi Eriksen</p>
</body></document>
